st_cookies_manager/__init__.py
st_cookies_manager/cookie_manager.py
st_cookies_manager/encrypted_cookie_manager.py
st_cookies_manager/package.json
st_cookies_manager/public/index.html
st_cookies_manager/src/index.ts
st_cookies_manager/src/react-app-env.d.ts
st_cookies_manager/tsconfig.json
st_cookies_manager-0.2.1.dist-info/METADATA
st_cookies_manager-0.2.1.dist-info/WHEEL
st_cookies_manager-0.2.1.dist-info/RECORD
